<?xml version="1.0"?>

<bindings xmlns="http://www.mozilla.org/xbl"
    xmlns:xbl="http://www.mozilla.org/xbl"
    xmlns:html="http://www.w3.org/1999/xhtml"
    xmlns:xul="http://www.mozilla.org/keymaster/gatekeeper/there.is.only.xul">

  <binding id="info">

    <resources>
      <stylesheet src="chrome://global/skin"/>
      <stylesheet src="chrome://oneteam/skin/contactinfo/contactinfo.css"/>
    </resources>

    <content>
      <xul:hbox id="contact-info-box" flex="1">
        <xul:avatar id="avatar" showBlankAvatar="true"/>
        <xul:vbox id="conferenceIcon" hidden="true">
          <xul:image id="conferenceIconImage"/>
        </xul:vbox>
        <xul:vbox flex="1">
          <xul:description id="name" flex="1">
            <xul:label id="jid"/>
          </xul:description>
          <xul:description id="subject" hidden="true"/>
          <xul:hbox align="center">
            <xul:image id="statusIcon"/>
            <xul:label id="status"/>
            <xul:label flex="1" crop="end" id="statusText"/>
          </xul:hbox>
        </xul:vbox>
      </xul:hbox>
    </content>

    <implementation>

      <property name="model" onget="return this._model">
        <setter><![CDATA[
          if (this._model == val)
            return val;

          if (!this._avatar) {
            this._model = val;
            return val;
          }

          // XXX: Should be val instanceof Conference but may not work in other
          //  windows
          var modelIsConference = !!(val && val.joinRoom);

          this._subject.hidden = !modelIsConference;
          this._status.parentNode.hidden = modelIsConference;
          this._avatar.hidden = modelIsConference;
          document.getAnonymousElementByAttribute(this, "id", "conferenceIcon").
            hidden = !modelIsConference;

          if (this._token) {
            this._token = this._model.unregisterView(this._token);
            this._token2 = this._model.unregisterView(this._token2);
          }

          this._model = val;

          if (val) {
            this._token = this._model.registerView(this.onNameChange, this, "visibleName");
            if (modelIsConference)
              this._token2 = this._model.registerView(this.onSubjectChanged, this, "subject");
            else
              this._token2 = this._model.registerView(this.onPresenceChange, this, "presence");
          } else
            this._token = this._token2 = null;

          this.onSubjectChanged();
          this.onNameChange();
          this.onPresenceChange();

          this._avatar.model = modelIsConference ? null : val;

          return val;
        ]]></setter>
      </property>

      <constructor>
        <![CDATA[
          this._avatar = document.getAnonymousElementByAttribute(this, "id", "avatar");
          this._name = document.getAnonymousElementByAttribute(this, "id", "name");
          this._jid = document.getAnonymousElementByAttribute(this, "id", "jid");
          this._subject = document.getAnonymousElementByAttribute(this, "id", "subject");
          this._status = document.getAnonymousElementByAttribute(this, "id", "status");
          this._statusIcon = document.getAnonymousElementByAttribute(this, "id", "statusIcon");
          this._statusText = document.getAnonymousElementByAttribute(this, "id", "statusText");

          var root = window;

          while (!root.account)
            root = root.opener;

          this._unavailablePresence = new root.Presence("unavailable");

          if (this.model) {
            var model = this.model;
            delete this.model;
            this._model = null;
            this.model = model;
          }
        ]]>
      </constructor>

      <destructor>
        <![CDATA[
          this.model = null;
        ]]>
      </destructor>

      <method name="onNameChange">
        <body><![CDATA[
          while (this._name.firstChild != this._jid)
            this._name.removeChild(this._name.firstChild);

          if (this.model) {
            this._name.insertBefore(document.createTextNode(this.model.visibleName),
                                    this._jid);
            this._jid.value = " ("+this.model.jid+")";
          } else {
            this._jid.value = "";
          }
        ]]></body>
      </method>

      <method name="onPresenceChange">
        <body><![CDATA[
          if (this.model) {
            this._statusIcon.src = this.model.getStatusIcon();
            this._status.value = this.model.presence;
            this._status.style.color = this.model.presence.getColor();
            this._statusText.value = this.model.presence.status ?
              " - "+this.model.presence.status : "";
          } else {
            this._statusIcon.src = this._unavailablePresence.getIcon();
            this._status.value = this._unavailablePresence;
            this._status.style.color = this._unavailablePresence.getColor();
            this._statusText.value = "";
          }
        ]]></body>
      </method>

      <method name="onSubjectChanged">
        <body><![CDATA[
          var subject = (this._model && this._model.subject) || "";

          if (this._subject.firstChild)
            this._subject.firstChild.replaceData(0, 0xffff, subject);
          else
            this._subject.appendChild(document.createTextNode(subject));
        ]]></body>
      </method>
    </implementation>

  </binding>

</bindings>
